metaDKQ.cp38-win_amd64.pyd
metaDKT.cp38-win_amd64.pyd
metaGQ12.cp38-win_amd64.pyd
metaT9.cp38-win_amd64.pyd
metaTMQb.cp38-win_amd64.pyd
metaTMQs.cp38-win_amd64.pyd
hyperstatic/__init__.py
hyperstatic/app/__init__.py
hyperstatic/app/general/__init__.py
hyperstatic/app/general/db.py
hyperstatic/app/general/model.py
hyperstatic/app/general/orm.py
hyperstatic/app/general/environment/__init__.py
hyperstatic/app/general/environment/curve.py
hyperstatic/app/general/environment/project.py
hyperstatic/app/general/io/__init__.py
hyperstatic/app/general/io/dxf.py
hyperstatic/app/general/io/s2k.py
hyperstatic/app/general/load/__init__.py
hyperstatic/app/general/load/loadcase.py
hyperstatic/app/general/load/pattern.py
hyperstatic/app/general/object/__init__.py
hyperstatic/app/general/object/area.py
hyperstatic/app/general/object/frame.py
hyperstatic/app/general/object/joint.py
hyperstatic/app/general/post/__init__.py
hyperstatic/app/general/post/combination.py
hyperstatic/app/general/property/__init__.py
hyperstatic/app/general/property/area_section.py
hyperstatic/app/general/property/frame_section.py
hyperstatic/app/general/property/material.py
hyperstatic/app/general/result/__init__.py
hyperstatic/app/general/result/result.py
hyperstatic/app/general/solve/__init__.py
hyperstatic/app/scripts/__init__.py
hyperstatic/app/scripts/io/__init__.py
hyperstatic/app/seismic/__init__.py
hyperstatic/app/seismic/spec2wave.py
hyperstatic/app/seismic/wave2spec.py
hyperstatic/app/seismic/wave_selection.py
hyperstatic/app/viz/__init__.py
hyperstatic/app/viz/viz_core/__init__.py
hyperstatic/app/viz/viz_core/model_basic.py
hyperstatic/app/viz/viz_core/model_load.py
hyperstatic/app/viz/viz_core/result_deformation.py
hyperstatic/app/viz/viz_core/viz_core_model.py
hyperstatic/app/viz/viz_core/viz_core_result_deformation.py
hyperstatic/common/__init__.py
hyperstatic/common/csys.py
hyperstatic/common/curve.py
hyperstatic/common/logger.py
hyperstatic/common/tolerance.py
hyperstatic/core/__init__.py
Hyperstatic-0.2.0.dist-info/LICENSE
Hyperstatic-0.2.0.dist-info/METADATA
Hyperstatic-0.2.0.dist-info/WHEEL
Hyperstatic-0.2.0.dist-info/top_level.txt
Hyperstatic-0.2.0.dist-info/RECORD
